commune/__init__.py
commune-0.0.1.dist-info/LICENSE
commune-0.0.1.dist-info/METADATA
commune-0.0.1.dist-info/WHEEL
commune-0.0.1.dist-info/top_level.txt
commune-0.0.1.dist-info/RECORD
